pdf2zh/__init__.py
pdf2zh/backend.py
pdf2zh/cache.py
pdf2zh/config.py
pdf2zh/converter.py
pdf2zh/doclayout.py
pdf2zh/gui.py
pdf2zh/high_level.py
pdf2zh/mcp_server.py
pdf2zh/pdf2zh.py
pdf2zh/pdfinterp.py
pdf2zh/translator.py
pdf2zh-1.9.10.dist-info/METADATA
pdf2zh-1.9.10.dist-info/WHEEL
pdf2zh-1.9.10.dist-info/entry_points.txt
pdf2zh-1.9.10.dist-info/licenses/LICENSE
pdf2zh-1.9.10.dist-info/RECORD
