Metadata-Version: 2.4
Name: pdf2zh
Version: 1.9.10
Summary: Latex PDF Translator
Project-URL: Homepage, https://github.com/Byaidu/PDFMathTranslate
Author-email: Byaidu <byaidux@gmail.com>
License-Expression: AGPL-3.0
License-File: LICENSE
Classifier: Operating System :: OS Independent
Classifier: Programming Language :: Python :: 3
Requires-Python: <3.13,>=3.10
Requires-Dist: azure-ai-translation-text<=1.0.1
Requires-Dist: babeldoc<0.3.0,>=0.1.22
Requires-Dist: deepl
Requires-Dist: fonttools
Requires-Dist: gradio
Requires-Dist: gradio-pdf>=0.0.21
Requires-Dist: huggingface-hub
Requires-Dist: numpy
Requires-Dist: ollama
Requires-Dist: onnx
Requires-Dist: onnxruntime
Requires-Dist: openai>=1.0.0
Requires-Dist: opencv-python-headless
Requires-Dist: pdfminer-six==20250416
Requires-Dist: peewee>=3.17.8
Requires-Dist: pikepdf
Requires-Dist: pymupdf<1.25.3
Requires-Dist: requests
Requires-Dist: rich
Requires-Dist: tenacity
Requires-Dist: tencentcloud-sdk-python-tmt
Requires-Dist: tqdm
Requires-Dist: xinference-client
Provides-Extra: argostranslate
Requires-Dist: argostranslate; extra == 'argostranslate'
Provides-Extra: backend
Requires-Dist: celery; extra == 'backend'
Requires-Dist: flask; extra == 'backend'
Requires-Dist: redis; extra == 'backend'
Provides-Extra: mcp
Requires-Dist: mcp>=1.6.0; extra == 'mcp'
